agent_attention_pytorch/__init__.py
agent_attention_pytorch/agent_attention_pytorch.py
agent_attention_pytorch/agent_transformer.py
agent_attention_pytorch-0.1.7.dist-info/LICENSE
agent_attention_pytorch-0.1.7.dist-info/METADATA
agent_attention_pytorch-0.1.7.dist-info/WHEEL
agent_attention_pytorch-0.1.7.dist-info/top_level.txt
agent_attention_pytorch-0.1.7.dist-info/RECORD
