Metadata-Version: 2.1
Name: agent-attention-pytorch
Version: 0.1.7
Summary: Agent Attention - Pytorch
Home-page: https://github.com/lucidrains/agent-attention-pytorch
Author: Phil Wang
Author-email: lucidrains@gmail.com
License: MIT
Keywords: artificial intelligence,deep learning,attention,linear attention
Classifier: Development Status :: 4 - Beta
Classifier: Intended Audience :: Developers
Classifier: Topic :: Scientific/Engineering :: Artificial Intelligence
Classifier: License :: OSI Approved :: MIT License
Classifier: Programming Language :: Python :: 3.6
License-File: LICENSE
Requires-Dist: einops >=0.7.0
Requires-Dist: torch >=2.0
